fast_scrape-0.2.0.dist-info/METADATA
fast_scrape-0.2.0.dist-info/WHEEL
scrape_rs/__init__.py
scrape_rs/__init__.pyi
scrape_rs/_core.cpython-310-aarch64-linux-gnu.so
scrape_rs/py.typed
fast_scrape-0.2.0.dist-info/RECORD
