Metadata-Version: 2.4
Name: fast-scrape
Version: 0.2.0
Classifier: Development Status :: 3 - Alpha
Classifier: Intended Audience :: Developers
Classifier: License :: OSI Approved :: MIT License
Classifier: License :: OSI Approved :: Apache Software License
Classifier: Operating System :: OS Independent
Classifier: Programming Language :: Python :: 3
Classifier: Programming Language :: Python :: 3.10
Classifier: Programming Language :: Python :: 3.11
Classifier: Programming Language :: Python :: 3.12
Classifier: Programming Language :: Python :: 3.13
Classifier: Programming Language :: Python :: 3.14
Classifier: Programming Language :: Rust
Classifier: Topic :: Text Processing :: Markup :: HTML
Classifier: Typing :: Typed
Summary: High-performance HTML parsing library for Python
Keywords: html,parser,scraping,css-selectors,dom
License: MIT OR Apache-2.0
Requires-Python: >=3.10
Project-URL: Documentation, https://github.com/bug-ops/scrape-rs
Project-URL: Homepage, https://github.com/bug-ops/scrape-rs
Project-URL: Issues, https://github.com/bug-ops/scrape-rs/issues
Project-URL: Repository, https://github.com/bug-ops/scrape-rs
